hhharea/__init__.py
hhharea/circle.py
hhharea/rectangle.py
hhharea-0.1.0.dist-info/METADATA
hhharea-0.1.0.dist-info/WHEEL
hhharea-0.1.0.dist-info/top_level.txt
hhharea-0.1.0.dist-info/RECORD
