Metadata-Version: 2.1
Name: hhharea
Version: 0.1.0
Summary: Calculation of area of shapes
Home-page: https://rkpackage.com/hhharea
Author: Rajiv Karbhal
Author-email: rajivkarbhal@gmail.com
License: UNKNOWN
Platform: UNKNOWN
Classifier: Programming Language :: Python :: 3
Classifier: License :: OSI Approved :: MIT License
Classifier: Operating System :: OS Independent
